Fay/__init__.py
Fay/dlt.py
Fay/fay_booter.py
Fay/main.py
Fay-0.1.1.1.1.dist-info/METADATA
Fay-0.1.1.1.1.dist-info/WHEEL
Fay-0.1.1.1.1.dist-info/top_level.txt
Fay-0.1.1.1.1.dist-info/RECORD
