Metadata-Version: 2.1
Name: Fay
Version: 0.1.1.1.1
Summary: Fay is an open-source digital human framework integrating language models and digital characters. It offers retail, assistant, and agent versions for diverse applications like virtual shopping guides, broadcasters, assistants, waiters, teachers, and voice or text-based mobile assistants.
Home-page: https://github.com/xszyou/Fay/tree/fay-assistant-edition
Author: Fay
Author-email: xszyou@yaheen.com
License: MIT
Requires-Python: >=3.6
Requires-Dist: requests
Requires-Dist: numpy
Requires-Dist: websockets (~=10.2)
Requires-Dist: ws4py (~=0.5.1)
Requires-Dist: pyaudio (~=0.2.11)
Requires-Dist: flask (~=3.0.0)
Requires-Dist: openpyxl (~=3.0.9)
Requires-Dist: pygame (~=2.1.2)
Requires-Dist: flask-cors (~=3.0.10)
Requires-Dist: PyQtWebEngine (~=5.15.5)
Requires-Dist: eyed3 (~=0.9.6)
Requires-Dist: websocket-client
Requires-Dist: azure-cognitiveservices-speech
Requires-Dist: aliyun-python-sdk-core (==2.13.3)
Requires-Dist: scipy (~=1.10.0)
Requires-Dist: simhash
Requires-Dist: pytz
Requires-Dist: gevent (~=22.10.1)
Requires-Dist: edge-tts (~=6.1.3)
Requires-Dist: ultralytics (~=8.0.2)
Requires-Dist: pydub
Requires-Dist: cemotion
Requires-Dist: langchain (==0.0.336)
Requires-Dist: eyed3
Requires-Dist: chromadb
Requires-Dist: pyqt5 (~=5.15.6)
